{"_format":"","paths":{"artifacts":"out","build_infos":"out/build-info","sources":"src","tests":"test","scripts":"script","libraries":["lib"]},"files":{"lib/forge-std/src/Base.sol":{"lastModificationDate":1775392820625,"contentHash":"057da15af4544b7a","interfaceReprHash":null,"sourceName":"lib/forge-std/src/Base.sol","imports":["lib/forge-std/src/StdStorage.sol","lib/forge-std/src/Vm.sol"],"versionRequirement":">=0.8.13, <0.9.0","artifacts":{"CommonBase":{"0.8.34":{"default":{"path":"Base.sol\\CommonBase.json","build_id":"bc7a48028bbf5a06"}}},"ScriptBase":{"0.8.34":{"default":{"path":"Base.sol\\ScriptBase.json","build_id":"bc7a48028bbf5a06"}}},"TestBase":{"0.8.34":{"default":{"path":"Base.sol\\TestBase.json","build_id":"bc7a48028bbf5a06"}}}},"seenByCompiler":true},"lib/forge-std/src/StdAssertions.sol":{"lastModificationDate":1775393177421,"contentHash":"7abff84395700e95","interfaceReprHash":null,"sourceName":"lib/forge-std/src/StdAssertions.sol","imports":["lib/forge-std/src/Vm.sol"],"versionRequirement":">=0.8.13, <0.9.0","artifacts":{"StdAssertions":{"0.8.34":{"default":{"path":"StdAssertions.sol\\StdAssertions.json","build_id":"bc7a48028bbf5a06"}}}},"seenByCompiler":true},"lib/forge-std/src/StdChains.sol":{"lastModificationDate":1775392820629,"contentHash":"cef85f092f883921","interfaceReprHash":null,"sourceName":"lib/forge-std/src/StdChains.sol","imports":["lib/forge-std/src/Vm.sol"],"versionRequirement":">=0.8.13, <0.9.0","artifacts":{"StdChains":{"0.8.34":{"default":{"path":"StdChains.sol\\StdChains.json","build_id":"bc7a48028bbf5a06"}}}},"seenByCompiler":true},"lib/forge-std/src/StdCheats.sol":{"lastModificationDate":1775392820630,"contentHash":"906cd6276ed83364","interfaceReprHash":null,"sourceName":"lib/forge-std/src/StdCheats.sol","imports":["lib/forge-std/src/StdStorage.sol","lib/forge-std/src/Vm.sol","lib/forge-std/src/console.sol","lib/forge-std/src/console2.sol"],"versionRequirement":">=0.8.13, <0.9.0","artifacts":{"StdCheats":{"0.8.34":{"default":{"path":"StdCheats.sol\\StdCheats.json","build_id":"bc7a48028bbf5a06"}}},"StdCheatsSafe":{"0.8.34":{"default":{"path":"StdCheats.sol\\StdCheatsSafe.json","build_id":"bc7a48028bbf5a06"}}}},"seenByCompiler":true},"lib/forge-std/src/StdConstants.sol":{"lastModificationDate":1775392820631,"contentHash":"6e64e3e0f1e270b1","interfaceReprHash":null,"sourceName":"lib/forge-std/src/StdConstants.sol","imports":["lib/forge-std/src/Vm.sol","lib/forge-std/src/interfaces/IMulticall3.sol"],"versionRequirement":">=0.8.13, <0.9.0","artifacts":{"StdConstants":{"0.8.34":{"default":{"path":"StdConstants.sol\\StdConstants.json","build_id":"bc7a48028bbf5a06"}}}},"seenByCompiler":true},"lib/forge-std/src/StdError.sol":{"lastModificationDate":1775392820632,"contentHash":"aa3090ae1422ce31","interfaceReprHash":null,"sourceName":"lib/forge-std/src/StdError.sol","imports":[],"versionRequirement":">=0.8.13, <0.9.0","artifacts":{"stdError":{"0.8.34":{"default":{"path":"StdError.sol\\stdError.json","build_id":"bc7a48028bbf5a06"}}}},"seenByCompiler":true},"lib/forge-std/src/StdInvariant.sol":{"lastModificationDate":1775393177423,"contentHash":"b482f161ff5afe1f","interfaceReprHash":null,"sourceName":"lib/forge-std/src/StdInvariant.sol","imports":[],"versionRequirement":">=0.8.13, <0.9.0","artifacts":{"StdInvariant":{"0.8.34":{"default":{"path":"StdInvariant.sol\\StdInvariant.json","build_id":"bc7a48028bbf5a06"}}}},"seenByCompiler":true},"lib/forge-std/src/StdJson.sol":{"lastModificationDate":1775392820633,"contentHash":"deb75521f38fb99f","interfaceReprHash":null,"sourceName":"lib/forge-std/src/StdJson.sol","imports":["lib/forge-std/src/Vm.sol"],"versionRequirement":">=0.8.13, <0.9.0","artifacts":{"stdJson":{"0.8.34":{"default":{"path":"StdJson.sol\\stdJson.json","build_id":"bc7a48028bbf5a06"}}}},"seenByCompiler":true},"lib/forge-std/src/StdMath.sol":{"lastModificationDate":1775392820633,"contentHash":"393b2ec0becc479a","interfaceReprHash":null,"sourceName":"lib/forge-std/src/StdMath.sol","imports":[],"versionRequirement":">=0.8.13, <0.9.0","artifacts":{"stdMath":{"0.8.34":{"default":{"path":"StdMath.sol\\stdMath.json","build_id":"bc7a48028bbf5a06"}}}},"seenByCompiler":true},"lib/forge-std/src/StdStorage.sol":{"lastModificationDate":1775393177424,"contentHash":"841b0345e6acf8d0","interfaceReprHash":null,"sourceName":"lib/forge-std/src/StdStorage.sol","imports":["lib/forge-std/src/Vm.sol"],"versionRequirement":">=0.8.13, <0.9.0","artifacts":{"stdStorage":{"0.8.34":{"default":{"path":"StdStorage.sol\\stdStorage.json","build_id":"bc7a48028bbf5a06"}}},"stdStorageSafe":{"0.8.34":{"default":{"path":"StdStorage.sol\\stdStorageSafe.json","build_id":"bc7a48028bbf5a06"}}}},"seenByCompiler":true},"lib/forge-std/src/StdStyle.sol":{"lastModificationDate":1775392820635,"contentHash":"dd683e581612d9d7","interfaceReprHash":null,"sourceName":"lib/forge-std/src/StdStyle.sol","imports":["lib/forge-std/src/Vm.sol"],"versionRequirement":">=0.8.13, <0.9.0","artifacts":{"StdStyle":{"0.8.34":{"default":{"path":"StdStyle.sol\\StdStyle.json","build_id":"bc7a48028bbf5a06"}}}},"seenByCompiler":true},"lib/forge-std/src/StdToml.sol":{"lastModificationDate":1775392820635,"contentHash":"66561afcd2e48189","interfaceReprHash":null,"sourceName":"lib/forge-std/src/StdToml.sol","imports":["lib/forge-std/src/Vm.sol"],"versionRequirement":">=0.8.13, <0.9.0","artifacts":{"stdToml":{"0.8.34":{"default":{"path":"StdToml.sol\\stdToml.json","build_id":"bc7a48028bbf5a06"}}}},"seenByCompiler":true},"lib/forge-std/src/StdUtils.sol":{"lastModificationDate":1775392820636,"contentHash":"476c1e8becd32967","interfaceReprHash":null,"sourceName":"lib/forge-std/src/StdUtils.sol","imports":["lib/forge-std/src/StdConstants.sol","lib/forge-std/src/Vm.sol","lib/forge-std/src/interfaces/IMulticall3.sol"],"versionRequirement":">=0.8.13, <0.9.0","artifacts":{"StdUtils":{"0.8.34":{"default":{"path":"StdUtils.sol\\StdUtils.json","build_id":"bc7a48028bbf5a06"}}}},"seenByCompiler":true},"lib/forge-std/src/Test.sol":{"lastModificationDate":1775392820636,"contentHash":"bd0e131f71fa5665","interfaceReprHash":null,"sourceName":"lib/forge-std/src/Test.sol","imports":["lib/forge-std/src/Base.sol","lib/forge-std/src/StdAssertions.sol","lib/forge-std/src/StdChains.sol","lib/forge-std/src/StdCheats.sol","lib/forge-std/src/StdConstants.sol","lib/forge-std/src/StdError.sol","lib/forge-std/src/StdInvariant.sol","lib/forge-std/src/StdJson.sol","lib/forge-std/src/StdMath.sol","lib/forge-std/src/StdStorage.sol","lib/forge-std/src/StdStyle.sol","lib/forge-std/src/StdToml.sol","lib/forge-std/src/StdUtils.sol","lib/forge-std/src/Vm.sol","lib/forge-std/src/console.sol","lib/forge-std/src/console2.sol","lib/forge-std/src/interfaces/IMulticall3.sol","lib/forge-std/src/safeconsole.sol"],"versionRequirement":">=0.8.13, <0.9.0","artifacts":{"Test":{"0.8.34":{"default":{"path":"Test.sol\\Test.json","build_id":"bc7a48028bbf5a06"}}}},"seenByCompiler":true},"lib/forge-std/src/Vm.sol":{"lastModificationDate":1775392820638,"contentHash":"55e749aafb49ce93","interfaceReprHash":null,"sourceName":"lib/forge-std/src/Vm.sol","imports":[],"versionRequirement":">=0.8.13, <0.9.0","artifacts":{"Vm":{"0.8.34":{"default":{"path":"Vm.sol\\Vm.json","build_id":"bc7a48028bbf5a06"}}},"VmSafe":{"0.8.34":{"default":{"path":"Vm.sol\\VmSafe.json","build_id":"bc7a48028bbf5a06"}}}},"seenByCompiler":true},"lib/forge-std/src/console.sol":{"lastModificationDate":1775392820639,"contentHash":"c2f250cceea75093","interfaceReprHash":null,"sourceName":"lib/forge-std/src/console.sol","imports":[],"versionRequirement":">=0.8.13, <0.9.0","artifacts":{"console":{"0.8.34":{"default":{"path":"console.sol\\console.json","build_id":"bc7a48028bbf5a06"}}}},"seenByCompiler":true},"lib/forge-std/src/console2.sol":{"lastModificationDate":1775392820641,"contentHash":"fb84555cebe27360","interfaceReprHash":null,"sourceName":"lib/forge-std/src/console2.sol","imports":["lib/forge-std/src/console.sol"],"versionRequirement":">=0.8.13, <0.9.0","artifacts":{},"seenByCompiler":true},"lib/forge-std/src/interfaces/IMulticall3.sol":{"lastModificationDate":1775392820647,"contentHash":"731463c8fd01e759","interfaceReprHash":null,"sourceName":"lib/forge-std/src/interfaces/IMulticall3.sol","imports":[],"versionRequirement":">=0.8.13, <0.9.0","artifacts":{"IMulticall3":{"0.8.34":{"default":{"path":"IMulticall3.sol\\IMulticall3.json","build_id":"bc7a48028bbf5a06"}}}},"seenByCompiler":true},"lib/forge-std/src/safeconsole.sol":{"lastModificationDate":1775392820649,"contentHash":"075ad54247fa474a","interfaceReprHash":null,"sourceName":"lib/forge-std/src/safeconsole.sol","imports":[],"versionRequirement":">=0.8.13, <0.9.0","artifacts":{"safeconsole":{"0.8.34":{"default":{"path":"safeconsole.sol\\safeconsole.json","build_id":"bc7a48028bbf5a06"}}}},"seenByCompiler":true},"src/AMM.sol":{"lastModificationDate":1775395816780,"contentHash":"4738e0908571950d","interfaceReprHash":null,"sourceName":"src/AMM.sol","imports":["src/LPToken.sol","src/MyToken.sol"],"versionRequirement":"^0.8.20","artifacts":{"AMM":{"0.8.34":{"default":{"path":"AMM.sol\\AMM.json","build_id":"67ddc2168ced3106"}}}},"seenByCompiler":true},"src/Counter.sol":{"lastModificationDate":1775393172371,"contentHash":"11a918b87c723f51","interfaceReprHash":null,"sourceName":"src/Counter.sol","imports":[],"versionRequirement":"^0.8.13","artifacts":{"Counter":{"0.8.34":{"default":{"path":"Counter.sol\\Counter.json","build_id":"bc7a48028bbf5a06"}}}},"seenByCompiler":true},"src/LPToken.sol":{"lastModificationDate":1775396359693,"contentHash":"1c1303eb1ae5776c","interfaceReprHash":null,"sourceName":"src/LPToken.sol","imports":[],"versionRequirement":"^0.8.20","artifacts":{"LPToken":{"0.8.34":{"default":{"path":"LPToken.sol\\LPToken.json","build_id":"67ddc2168ced3106"}}}},"seenByCompiler":true},"src/LendingPool.sol":{"lastModificationDate":1775397489783,"contentHash":"9500fc7402eac1ca","interfaceReprHash":null,"sourceName":"src/LendingPool.sol","imports":["src/MyToken.sol"],"versionRequirement":"^0.8.20","artifacts":{"LendingPool":{"0.8.34":{"default":{"path":"LendingPool.sol\\LendingPool.json","build_id":"67ddc2168ced3106"}}}},"seenByCompiler":true},"src/MyToken.sol":{"lastModificationDate":1775392341336,"contentHash":"1f887cf19b12225b","interfaceReprHash":null,"sourceName":"src/MyToken.sol","imports":[],"versionRequirement":"^0.8.20","artifacts":{"MyToken":{"0.8.34":{"default":{"path":"MyToken.sol\\MyToken.json","build_id":"bc7a48028bbf5a06"}}}},"seenByCompiler":true},"test/Counter.t.sol":{"lastModificationDate":1775393172371,"contentHash":"f4793edc3fe87617","interfaceReprHash":null,"sourceName":"test/Counter.t.sol","imports":["lib/forge-std/src/Base.sol","lib/forge-std/src/StdAssertions.sol","lib/forge-std/src/StdChains.sol","lib/forge-std/src/StdCheats.sol","lib/forge-std/src/StdConstants.sol","lib/forge-std/src/StdError.sol","lib/forge-std/src/StdInvariant.sol","lib/forge-std/src/StdJson.sol","lib/forge-std/src/StdMath.sol","lib/forge-std/src/StdStorage.sol","lib/forge-std/src/StdStyle.sol","lib/forge-std/src/StdToml.sol","lib/forge-std/src/StdUtils.sol","lib/forge-std/src\\Test.sol","lib/forge-std/src/Vm.sol","lib/forge-std/src/console.sol","lib/forge-std/src/console2.sol","lib/forge-std/src/interfaces/IMulticall3.sol","lib/forge-std/src/safeconsole.sol","src\\Counter.sol"],"versionRequirement":"^0.8.13","artifacts":{"CounterTest":{"0.8.34":{"default":{"path":"Counter.t.sol\\CounterTest.json","build_id":"bc7a48028bbf5a06"}}}},"seenByCompiler":true},"test/Fork.t.sol":{"lastModificationDate":1775394359739,"contentHash":"39cfbf7836b099c2","interfaceReprHash":null,"sourceName":"test/Fork.t.sol","imports":["lib/forge-std/src/Base.sol","lib/forge-std/src/StdAssertions.sol","lib/forge-std/src/StdChains.sol","lib/forge-std/src/StdCheats.sol","lib/forge-std/src/StdConstants.sol","lib/forge-std/src/StdError.sol","lib/forge-std/src/StdInvariant.sol","lib/forge-std/src/StdJson.sol","lib/forge-std/src/StdMath.sol","lib/forge-std/src/StdStorage.sol","lib/forge-std/src/StdStyle.sol","lib/forge-std/src/StdToml.sol","lib/forge-std/src/StdUtils.sol","lib/forge-std/src\\Test.sol","lib/forge-std/src/Vm.sol","lib/forge-std/src/console.sol","lib/forge-std/src/console2.sol","lib/forge-std/src/interfaces/IMulticall3.sol","lib/forge-std/src/safeconsole.sol"],"versionRequirement":"^0.8.20","artifacts":{"ForkTest":{"0.8.34":{"default":{"path":"Fork.t.sol\\ForkTest.json","build_id":"c309ef1dd9af0b04"}}},"IERC20":{"0.8.34":{"default":{"path":"Fork.t.sol\\IERC20.json","build_id":"c309ef1dd9af0b04"}}},"IUniswapV2Router":{"0.8.34":{"default":{"path":"Fork.t.sol\\IUniswapV2Router.json","build_id":"c309ef1dd9af0b04"}}}},"seenByCompiler":true},"test/LendingPool.t.sol":{"lastModificationDate":1775397470414,"contentHash":"7f35a07793d09d67","interfaceReprHash":null,"sourceName":"test/LendingPool.t.sol","imports":["lib/forge-std/src/Base.sol","lib/forge-std/src/StdAssertions.sol","lib/forge-std/src/StdChains.sol","lib/forge-std/src/StdCheats.sol","lib/forge-std/src/StdConstants.sol","lib/forge-std/src/StdError.sol","lib/forge-std/src/StdInvariant.sol","lib/forge-std/src/StdJson.sol","lib/forge-std/src/StdMath.sol","lib/forge-std/src/StdStorage.sol","lib/forge-std/src/StdStyle.sol","lib/forge-std/src/StdToml.sol","lib/forge-std/src/StdUtils.sol","lib/forge-std/src\\Test.sol","lib/forge-std/src/Vm.sol","lib/forge-std/src/console.sol","lib/forge-std/src/console2.sol","lib/forge-std/src/interfaces/IMulticall3.sol","lib/forge-std/src/safeconsole.sol","src/LendingPool.sol","src/MyToken.sol"],"versionRequirement":"^0.8.20","artifacts":{"LendingPoolTest":{"0.8.34":{"default":{"path":"LendingPool.t.sol\\LendingPoolTest.json","build_id":"67ddc2168ced3106"}}}},"seenByCompiler":true},"test/MyToken.t.sol":{"lastModificationDate":1775393317017,"contentHash":"8f2aae6e86d21a17","interfaceReprHash":null,"sourceName":"test/MyToken.t.sol","imports":["lib/forge-std/src/Base.sol","lib/forge-std/src/StdAssertions.sol","lib/forge-std/src/StdChains.sol","lib/forge-std/src/StdCheats.sol","lib/forge-std/src/StdConstants.sol","lib/forge-std/src/StdError.sol","lib/forge-std/src/StdInvariant.sol","lib/forge-std/src/StdJson.sol","lib/forge-std/src/StdMath.sol","lib/forge-std/src/StdStorage.sol","lib/forge-std/src/StdStyle.sol","lib/forge-std/src/StdToml.sol","lib/forge-std/src/StdUtils.sol","lib/forge-std/src\\Test.sol","lib/forge-std/src/Vm.sol","lib/forge-std/src/console.sol","lib/forge-std/src/console2.sol","lib/forge-std/src/interfaces/IMulticall3.sol","lib/forge-std/src/safeconsole.sol","src\\MyToken.sol"],"versionRequirement":"^0.8.20","artifacts":{"MyTokenTest":{"0.8.34":{"default":{"path":"MyToken.t.sol\\MyTokenTest.json","build_id":"fe05258683c18751"}}}},"seenByCompiler":true}},"builds":["67ddc2168ced3106","bc7a48028bbf5a06","c309ef1dd9af0b04","fe05258683c18751"],"profiles":{"default":{"solc":{"optimizer":{"enabled":false,"runs":200},"metadata":{"useLiteralContent":false,"bytecodeHash":"ipfs","appendCBOR":true},"outputSelection":{"*":{"*":["abi","evm.bytecode.object","evm.bytecode.sourceMap","evm.bytecode.linkReferences","evm.deployedBytecode.object","evm.deployedBytecode.sourceMap","evm.deployedBytecode.linkReferences","evm.deployedBytecode.immutableReferences","evm.methodIdentifiers","metadata"]}},"evmVersion":"osaka","viaIR":false,"libraries":{}},"vyper":{"evmVersion":"osaka","outputSelection":{"*":{"*":["abi","evm.bytecode","evm.deployedBytecode"]}}}}},"preprocessed":false,"mocks":[]}